energyplus_transition/__init__.py
energyplus_transition/__main__.py
energyplus_transition/configure.py
energyplus_transition/energyplus_path.py
energyplus_transition/gui.py
energyplus_transition/international.py
energyplus_transition/runner.py
energyplus_transition/transition_binary.py
energyplus_transition/transition_run_thread.py
energyplus_transition/icons/icon.icns
energyplus_transition/icons/icon.ico
energyplus_transition/icons/icon.png
energyplus_transition_tools-2.1.3.dist-info/LICENSE.txt
energyplus_transition_tools-2.1.3.dist-info/METADATA
energyplus_transition_tools-2.1.3.dist-info/WHEEL
energyplus_transition_tools-2.1.3.dist-info/entry_points.txt
energyplus_transition_tools-2.1.3.dist-info/top_level.txt
energyplus_transition_tools-2.1.3.dist-info/RECORD
